{
    "key": "group_aera_partners_page",
    "title": "Partners Page Settings",
    "fields": [
        {
            "key": "field_partners_cta_title",
            "label": "CTA Title",
            "name": "partners_cta_title",
            "type": "text",
            "instructions": "Title for the call-to-action section at the bottom of the page.",
            "required": false,
            "default_value": "Interested in becoming a partner?",
            "wrapper": {
                "width": "100"
            }
        },
        {
            "key": "field_partners_cta_text",
            "label": "CTA Button Text",
            "name": "partners_cta_text",
            "type": "text",
            "instructions": "Text for the call-to-action button.",
            "required": false,
            "default_value": "Schedule Demo",
            "wrapper": {
                "width": "50"
            }
        },
        {
            "key": "field_partners_cta_link",
            "label": "CTA Button Link",
            "name": "partners_cta_link",
            "type": "url",
            "instructions": "URL for the call-to-action button.",
            "required": false,
            "default_value": "/demo",
            "wrapper": {
                "width": "50"
            }
        }
    ],
    "location": [
        [
            {
                "param": "options_page",
                "operator": "==",
                "value": "acf-options-company-options"
            }
        ]
    ],
    "menu_order": 1,
    "position": "normal",
    "style": "default",
    "label_placement": "top",
    "instruction_placement": "label",
    "hide_on_screen": "",
    "active": true,
    "description": "Settings for the Partners page including CTA section configuration.",
    "show_in_rest": 1,
    "modified": 1735000000
}

